LICENSE
MANIFEST.in
README.mkd
setup.cfg
setup.py
examples/identifiers.py
examples/orbit.py
graffunc/__init__.py
graffunc/__main__.py
graffunc/commons.py
graffunc/conv_graph.py
graffunc/errors.py
graffunc/graffunc.py
graffunc/info.py
graffunc/path_search.py
graffunc/path_walk.py
graffunc/solving.py
graffunc/validator.py
graffunc.egg-info/PKG-INFO
graffunc.egg-info/SOURCES.txt
graffunc.egg-info/dependency_links.txt
graffunc.egg-info/not-zip-safe
graffunc.egg-info/requires.txt
graffunc.egg-info/top_level.txt
graffunc/test/__init__.py
graffunc/test/test_conv_graph.py
graffunc/test/test_graffunc.py
graffunc/test/test_solving.py